coreason_scribe/__init__.py
coreason_scribe/decorators.py
coreason_scribe/delta.py
coreason_scribe/inspector.py
coreason_scribe/main.py
coreason_scribe/matrix.py
coreason_scribe/models.py
coreason_scribe/pdf.py
coreason_scribe/server.py
coreason_scribe/signer.py
coreason_scribe/templates/css/style.css
coreason_scribe/templates/sds.html
coreason_scribe/utils/__init__.py
coreason_scribe/utils/logger.py
coreason_scribe-0.4.0.dist-info/METADATA
coreason_scribe-0.4.0.dist-info/WHEEL
coreason_scribe-0.4.0.dist-info/licenses/LICENSE
coreason_scribe-0.4.0.dist-info/licenses/NOTICE
coreason_scribe-0.4.0.dist-info/RECORD
