Metadata-Version: 2.4
Name: coreason_scribe
Version: 0.4.0
Summary: coreason-scribe
License: # The Prosperity Public License 3.0.0
License-File: LICENSE
License-File: NOTICE
Author: Gowtham A Rao
Author-email: gowtham.rao@coreason.ai
Requires-Python: >=3.11
Classifier: License :: Other/Proprietary License
Classifier: Programming Language :: Python :: 3.12
Classifier: Operating System :: OS Independent
Requires-Dist: anyio (>=4.12.1,<5.0.0)
Requires-Dist: coreason-identity (>=0.4.2,<0.5.0)
Requires-Dist: fastapi (>=0.115.0,<0.116.0)
Requires-Dist: gitpython (>=3.1.46,<4.0.0)
Requires-Dist: httpx (>=0.28.1,<0.29.0)
Requires-Dist: jinja2 (>=3.1.6,<4.0.0)
Requires-Dist: loguru (>=0.7.2,<0.8.0)
Requires-Dist: pydantic (>=2.12.5,<3.0.0)
Requires-Dist: python-multipart (>=0.0.20,<0.0.21)
Requires-Dist: pyyaml (>=6.0.3,<7.0.0)
Requires-Dist: types-pyyaml (>=6.0.12.20250915,<7.0.0.0)
Requires-Dist: uvicorn (>=0.34.0,<0.35.0)
Requires-Dist: weasyprint (>=68.0,<69.0)
Project-URL: Documentation, https://github.com/CoReason-AI/coreason-scribe
Project-URL: Homepage, https://github.com/CoReason-AI/coreason-scribe
Project-URL: Repository, https://github.com/CoReason-AI/coreason-scribe
